mfournisseur/Fournisseur.py
mfournisseur/__init__.py
moduleFournisseur-2.0.dist-info/METADATA
moduleFournisseur-2.0.dist-info/WHEEL
moduleFournisseur-2.0.dist-info/top_level.txt
moduleFournisseur-2.0.dist-info/RECORD
