Metadata-Version: 2.1
Name: moduleFournisseur
Version: 2.0
Summary: Bibliotheque de composant pour fournisseur
Home-page: UNKNOWN
Author: Douchet
Author-email: TDouchet@eni.fr
License: UNKNOWN
Platform: UNKNOWN
